apiclientforle/__init__.py
labelearth_api_python_client-2.170.0.dist-info/licenses/LICENSE
labelearthapiclient/__init__.py
labelearthapiclient/_auth.py
labelearthapiclient/_helpers.py
labelearthapiclient/channel.py
labelearthapiclient/discovery.py
labelearthapiclient/errors.py
labelearthapiclient/http.py
labelearthapiclient/mimeparse.py
labelearthapiclient/model.py
labelearthapiclient/sample_tools.py
labelearthapiclient/schema.py
labelearthapiclient/version.py
labelearthapiclient/discovery_cache/__init__.py
labelearthapiclient/discovery_cache/appengine_memcache.py
labelearthapiclient/discovery_cache/base.py
labelearthapiclient/discovery_cache/file_cache.py
labelearthapiclient/discovery_cache/documents/abusiveexperiencereport.v1.json
labelearthapiclient/discovery_cache/documents/acceleratedmobilepageurl.v1.json
labelearthapiclient/discovery_cache/documents/accessapproval.v1.json
labelearthapiclient/discovery_cache/documents/accesscontextmanager.v1.json
labelearthapiclient/discovery_cache/documents/accesscontextmanager.v1beta.json
labelearthapiclient/discovery_cache/documents/acmedns.v1.json
labelearthapiclient/discovery_cache/documents/addressvalidation.v1.json
labelearthapiclient/discovery_cache/documents/adexchangebuyer.v1.2.json
labelearthapiclient/discovery_cache/documents/adexchangebuyer.v1.3.json
labelearthapiclient/discovery_cache/documents/adexchangebuyer.v1.4.json
labelearthapiclient/discovery_cache/documents/adexchangebuyer2.v2beta1.json
labelearthapiclient/discovery_cache/documents/adexperiencereport.v1.json
labelearthapiclient/discovery_cache/documents/admin.datatransfer_v1.json
labelearthapiclient/discovery_cache/documents/admin.datatransferv1.json
labelearthapiclient/discovery_cache/documents/admin.directory_v1.json
labelearthapiclient/discovery_cache/documents/admin.directoryv1.json
labelearthapiclient/discovery_cache/documents/admin.reports_v1.json
labelearthapiclient/discovery_cache/documents/admin.reportsv1.json
labelearthapiclient/discovery_cache/documents/admob.v1.json
labelearth_api_python_client-2.170.0.dist-info/METADATA
labelearth_api_python_client-2.170.0.dist-info/WHEEL
labelearth_api_python_client-2.170.0.dist-info/top_level.txt
labelearth_api_python_client-2.170.0.dist-info/RECORD
